testlibpy/__init__.py
testlibpy/functions.py
testlibpy-0.0.3.dist-info/METADATA
testlibpy-0.0.3.dist-info/WHEEL
testlibpy-0.0.3.dist-info/top_level.txt
testlibpy-0.0.3.dist-info/RECORD
