Metadata-Version: 2.1
Name: testlibpy
Version: 0.0.3
Summary: 工具包的简要说明
Home-page: https://xxxxxx.com/testlibpy
Author: pystudy
Author-email: xxxxxx@xxxxxx.com
License: MIT
Platform: UNKNOWN
Classifier: Development Status :: 3 - Alpha
Classifier: Programming Language :: Python :: 3
Classifier: Operating System :: OS Independent
Requires-Python: >=3.6
Requires-Dist: numpy (>1.15)
